{
  "timestamp": "2026-02-13T23:08:09.291146",
  "constants": {
    "target_concentration_ug_m3": 37.5,
    "basin_area_km2": 1500,
    "basin_length_km": 80
  },
  "atmospheric_conditions": {
    "blh_avg_m": 570.0,
    "wind_speed_avg_kmh": 6.95,
    "wind_speed_avg_ms": 1.93
  },
  "calculated_values": {
    "volume_m3": 855000000000.0,
    "residence_time_seconds": 41436.0,
    "residence_time_hours": 11.5,
    "emission_cap_ug_s": 773792367.0
  },
  "result": {
    "emission_cap_tons_day": 66.86
  }
}